LICENSE.txt
MANIFEST.in
README.rst
install_deps.sh
setup.cfg
setup.py
tox.ini
doc2text/__init__.py
doc2text/page.py
doc2text.egg-info/PKG-INFO
doc2text.egg-info/SOURCES.txt
doc2text.egg-info/dependency_links.txt
doc2text.egg-info/entry_points.txt
doc2text.egg-info/requires.txt
doc2text.egg-info/top_level.txt
tests/__init__.py
tests/test_simple.py