Metadata-Version: 1.1
Name: doc2text
Version: 0.2.3
Summary: doc2text drastically improves the extraction of text from images by fixing resolution, text area (crop), and skew.
Home-page: https://github.com/jlsutherland/doc2text
Author: Joseph L. Sutherland
Author-email: joe@clvr.tech
License: MIT
Keywords: ocr text detection machine learning computer vision
Platform: UNKNOWN
Classifier: Development Status :: 3 - Alpha
Classifier: Intended Audience :: Science/Research
Classifier: Topic :: Scientific/Engineering :: Image Recognition
Classifier: License :: OSI Approved :: MIT License
Classifier: Programming Language :: Python :: 2.7
Classifier: Programming Language :: Python :: 3.5
